{
  "processed": [
    "001",
    "002",
    "003",
    "004",
    "005",
    "006",
    "007",
    "008",
    "009",
    "010"
  ],
  "lastRun": "2026-05-17T06:53:00.000Z",
  "currentTopic": {
    "id": "011",
    "title": "長篠 の戦い 鉄砲を変えた戦場",
    "category": "合戦軸"
  },
  "lastScriptChars": 23122,
  "lastScriptChapters": [
    {
      "index": 1,
      "title": "éè£ããç¾©å£«ãããã®ç·ã®åã¯åç§",
      "chars": 3819
    },
    {
      "index": 2,
      "title": "è¬ã«åã¾ããååçã¨ç¢ºããªæè¦",
      "chars": 4965
    },
    {
      "index": 3,
      "title": "ä¿¡é·ãè¦åºããåãäºäººã®èææä»£",
      "chars": 4505
    },
    {
      "index": 4,
      "title": "å¿ã³å¯ãä¸åãå¿ã«ç¯ãçå¿µã®ç",
      "chars": 4128
    },
    {
      "index": 5,
      "title": "æã¯ä»ãå¤©ãä¸ãããæ¬è½å¯ºã¸ã®é",
      "chars": 5589
    }
  ],
  "lastVoiceAt": "2026-05-16T12:00:05.031Z",
  "lastImageGenAt": "2026-05-16T12:01:47.737Z",
  "videoStatus": "pending",
  "lastImageSources": [
    "https://upload.wikimedia.org/wikipedia/commons/c/c3/Akechi_Mitsuhide8.jpg",
    "https://upload.wikimedia.org/wikipedia/commons/d/da/Akechi_Mituharu.jpg",
    "https://upload.wikimedia.org/wikipedia/commons/d/d5/Akechi_Mitsutada.jpg",
    "https://upload.wikimedia.org/wikipedia/commons/8/8d/Trace_of_Akechi_Castle-A.JPG"
  ],
  "note_fix": "Manual state recovery 2026-05-17 by dispatch: 009 ç³ç°ä¸æ uploaded but state commit failed",
  "note_fix2": "Manual recovery 2026-05-17 for #010 çç°å¹¸æ upload (Upload to YouTube succeeded but state commit conflict)",
  "note_fix3": "Manual fix 2026-05-17: removed #011 é·ç¯  from processed - bad subtitles, re-generate with verify_subtitles guard"
}