{
  "id": "086",
  "topic_id": "086",
  "title": "坂本龍馬 海援隊と亀山社中の理想",
  "category": "人物軸",
  "description": "土佐の風雲児・坂本龍馬がいかにして幕末の荒波を越え、日本を変える組織「亀山社中・海援隊」を創り上げたのか。黒船の衝撃から世界を見据えた龍馬の知られざる苦悩と革新的な思想を紐解く、30分の歴史ドキュメンタリー。\n\n武士という身分の狭間で育った少年時代から、剣術修行、そして海軍という新たな道への覚醒まで。龍馬が抱いた「日本を世界へ漕ぎ出させる」という壮大な夢の全貌を、臨場感あふれるナレーションで徹底解説します。\n\n【本動画の章立て】\n0:00 第1章：土佐の風に吹かれて\n6:00 第2章：剣の深淵と時代の胎動\n12:00 第3章：黒船が変えた龍馬の視座\n18:00 第4章：亀山社中という革命的組織\n24:00 第5章：海援隊と龍馬の遺産\n\n歴史の裏側に隠された「龍馬の眼差し」を、ぜひ最後までお楽しみください。\n\n■チャンネル概要\n歴史の転換点に立ち尽くした人物の心情と決断を、深く掘り下げる歴史教養チャンネルです。チャンネル登録で、歴史の深淵を巡る旅へ。\n\n#坂本龍馬 #幕末 #歴史ドキュメンタリー #海援隊 #亀山社中 #日本史 #明治維新 #偉人伝 #歴史解説 #土佐藩",
  "tags": [
    "坂本龍馬",
    "幕末",
    "歴史",
    "海援隊",
    "亀山社中",
    "人物伝",
    "日本史",
    "明治維新",
    "ドキュメンタリー",
    "歴史解説"
  ],
  "thumbnail_text": "龍馬が見た未来\n海援隊の真実",
  "chapters": [
    {
      "index": 1,
      "title": "土佐の風に吹かれて",
      "narration": "土佐の地、鏡川の流れは古より変わることなく、南国の空の下を静かに流れている。この風土の中に、後の世を大きく揺るがすことになる一人の男が産声を上げた。坂本龍馬。郷士という、武士でありながら武士ではない、中途半端な身分。その狭間で彼は、武士としての矜持と、実社会の冷たさを同時に吸い込んで育った。\n\n幼き龍馬は、決して秀才とは言えなかった。泣き虫で、鼻垂れで、誰よりも甘えん坊。だが、その瞳の奥には、すでにこの国の行く末を映し出すための、広大な余白が広がっていたのかもしれない。剣術という道に身を投じたのは、己の未熟さを知っていたからに他ならない。剣を振るうことは、自分自身を鍛え直すことであり、己の生きるべき道を見定めるための儀式であった。\n\n江戸の千葉道場へと旅立った龍馬は、北辰一刀流の門を叩き、剣の深淵に触れる。そこで彼が学んだのは、ただ敵を倒す術ではない。相手の呼吸を読み、場の空気を支配し、一瞬の隙を見逃さぬ集中力。その研ぎ澄まされた感覚こそが、後の海援隊や亀山社中において、彼が数多の志士たちを束ね、荒波を渡るための武器となったのだ。\n\nだが、龍馬の若き日々を決定的に変えた出来事がある。嘉永六年、浦賀の海に浮かんだ巨大な黒い影。黒船である。泰平の眠りを貪っていた日本という国が、初めて異国の暴力的なまでの文明の力に直面した瞬間だった。多くの人々が恐怖に震え、鎖国という古き壁にしがみつく中、龍馬はただ一人、その甲板の上に立つ異国の男たちの背中を見つめていた。\n\n彼は、その巨大な鉄の塊に、未来の日本の姿を重ね合わせたのかもしれない。海を越えてやってきた黒船は、日本がどれほど狭い世界に閉じこもっていたかを冷酷なまでに突きつけた。もはや、刀一本で国を守る時代は終わろうとしている。彼の中に芽生えたのは、恐怖ではなく、尽きることのない好奇心と、この国を世界という大海原へと漕ぎ出させるという、壮大な覚悟であった。\n\n龍馬は日記に記した言葉がある。国を憂う心とは、ただ敵を憎むことではない。世界を知り、自らを変え、新しい時代の設計図を自らの手で描き出すことだ。亀山社中の設立へと繋がる彼の思想の原点は、まさにこの黒船の来航という、国難の現場にあった。土佐という小さな枠組みから脱し、日本という国そのものを一つの船として捉える視座。それが、若き日の龍馬の脳裏に、確固たるものとして刻み込まれた。\n\n剣を握り、修行に明け暮れた青春の季節は、彼にとっての助走であった。人は、己の無力さを知ったとき、真に強くなる。龍馬は、自分自身の弱さを認め、だからこそ他者の知恵を借り、時代の流れに抗うのではなく、その流れを自らの力で舵取りしようとした。海援隊という組織が、後にただの航海者集団を超えて、日本という国の未来を設計する場所となったのは、この若き日の苦悩と鍛錬があったからである。\n\n土佐の風は、今日も変わらずに吹いている。龍馬が眺めた海は、今もどこか寂しげに、そして雄大に広がっている。彼は、誰よりも土佐を愛し、同時に土佐という枠組みに収まりきれない魂を持っていた。郷士という身分の壁、藩という組織の論理、それらすべてが、龍馬にとっては、越えるべき小さな波に過ぎなかった。\n\n若き日の龍馬が見ていたのは、どこか遠い未来の光景である。亀山社中の結成という、あの独創的で、あまりにも無謀な試みを成功させたのも、この時の彼が抱いた「世界への憧憬」が消えることはなかったからだ。侍の美学とは、散る時の潔さだけを指すのではない。己の志のために、泥にまみれ、風に吹かれ、それでもなお、理想という名の星を見失わぬ強靭な生き様のことである。\n\n土佐の少年は、やがて日本を背負う男へと変貌を遂げていく。その過程で見せた、迷いのない眼差し。そして、何事にも捉われぬ自由な魂。彼の少年時代を知る者は、誰もが龍馬という男の底知れぬ器の大きさに驚いたという。だが、龍馬にとって、それは特別なことではなかった。ただ、目の前にある壁を突き破り、その先にある広い世界を見てみたかっただけなのだ。\n\n私たちは今、龍馬の歩んだ道を振り返る。そこには、一つの答えがある。時代がどれほど移ろい、文明がどれほど発達しようとも、己の魂を燃やし尽くすだけの何かを見つけられるかどうか。それが、人生を豊かにするための唯一の道筋であると。龍馬が青春のすべてを賭けて学んだのは、剣の技ではなく、己の魂をいかにして時代の荒波に放り込むか、という生きるための哲学であった。\n\n海援隊と亀山社中の理想は、龍馬が土佐の風に吹かれながら夢見た、自由で、開かれた日本という国の姿に他ならない。それは、特定の誰かのためのものではなく、この国に生きるすべての民のための未来であった。龍馬の生涯を紐解くことは、私たちの中に眠る「侍の魂」を呼び覚ますことと同義である。\n\nさあ、物語の続きへと進もう。土佐の風を背に受け、龍馬が次に向かったのは、長崎という名の、世界に開かれた扉であった。そこで彼がどのような夢を見、いかなる組織を立ち上げ、そして日本という国をどのように変えようとしたのか。その道程こそが、私たちの知るべき、真の歴史の輝きである。\n\n龍馬という男の背中には、常に海がある。そしてその海には、希望がある。たとえ時代が彼を翻弄しようとも、彼が抱いた志は、決して色あせることはない。土佐の風に吹かれて育った一人の青年が、いかにして日本という国の舵取りを担うようになったのか。その壮大な物語の幕開けを、今、私たちは目撃している。\n\n若き日の龍馬の瞳に映っていたものは、決して過去の遺産ではない。これから始まる、果てしない未来の光景であった。私たちは、彼が歩んだ足跡を辿ることで、自分自身の生き方をも問い直すことになるだろう。龍馬の美学、それは、何にも縛られず、何をも恐れず、ただ己の信じた道を突き進むという、気高き魂の軌跡である。\n\n龍馬は、知っていた。この国には、まだ誰も見たことのない景色が広がっていることを。それを手にするためには、まず自らが、古い慣習という名の殻を破らねばならない。亀山社中の旗揚げは、その最初の挑戦であった。土佐の風が彼を押し出し、時代の荒波が彼を鍛え上げた。すべては、この瞬間のためにあったのだ。\n\n歴史とは、記録された出来事の羅列ではない。その時代を生きた人々の、熱い鼓動の記録である。坂本龍馬という男の生涯は、まさにその鼓動そのものである。私たちは今、彼が土佐の風の中で誓った、あの遠い日の約束を思い出す。それは、日本という国を、真の意味で「自由」にするという約束であった。\n\n第1章の幕が降りようとしている。だが、龍馬の旅は、まだ始まったばかりである。長崎の地で彼を待ち受けていたのは、さらなる苦難と、それ以上に大きな希望であった。海援隊という名に込められた願い、そして亀山社中が示した、商という手段による革命。それらすべてが、龍馬の歩みと共に、歴史という名の広大な海へと繋がっていく。\n\n静寂が、物語の終わりを告げる。土佐の空は、今日もどこまでも青い。龍馬が駆け抜けた青春の日々は、今も日本の土壌に深く刻み込まれている。彼は、何を夢見、何を捨て、そして何を守ろうとしたのか。その真実を求めて、私たちは次なる時代へと歩みを進める。龍馬という侍が遺した美学を、その魂の在り処を、これから紐解いていくこととしよう。",
      "image_prompts": [
        "historic Japanese landscape, Tosa province countryside, Kagamigawa river, serene atmosphere",
        "historic Japanese young Ryoma Sakamoto, contemplative look, traditional samurai clothing",
        "historic Japanese samurai boy, practicing kendo, intense focus, late Edo period style"
      ]
    },
    {
      "index": 2,
      "title": "亀山社中という夜明けの夢",
      "narration": "剣術という道に身を投じたのち、江戸で開国論に触れ、攘夷と開国、二つの思想の狭間で激しく揺れ動いた龍馬は、やがて時代の大きなうねりの中で、ある決断を下す。それは、彼自身の運命を、そして日本の未来を大きく変えることになる、壮絶な覚悟の表れであった。\n\n文久二年、龍馬はついに土佐藩を脱藩する。故郷を捨て、主君への忠義を捨て、自らの命を顧みず、彼は荒波の世へと身を投じた。その背には、故郷を案じる家族の悲しみと、故郷を想う彼自身の断ち切れない情が、複雑に絡み合っていたに違いない。しかし、龍馬の心には、もはや私情を挟む余地はなかった。彼が見据えていたのは、一藩の利害を超えた、日本という国の夜明けであった。\n\n脱藩者という烙印は、彼を常に死と隣り合わせの状況に置いた。幕府の追手、藩の追っ手、そして攘夷論者からの命を狙う眼差し。しかし、龍馬は怯まなかった。彼の胸には、日本の未来を憂う、熱い志が燃え盛っていたからだ。彼は、既存の枠組みに囚われず、自らの手で新たな道を切り開くことを決意した。\n\nその第一歩として、龍馬が目指したのは、長崎の地であった。異国情緒漂う港町、長崎。そこは、西洋の文化と情報が流れ込み、日本の未来を予感させる、希望と混沌の坩堝であった。龍馬は、この地で、後の日本を動かすことになる、ある組織を結成する。それが、日本初の株式会社とも称される「亀山社中」である。\n\n「亀山社中」。その響きは、当時の日本において、異彩を放っていた。武士が商いをすることなど、あってはならないこと。しかし、龍馬は、その常識を打ち破った。彼は、武士の身分を捨て、あえて商人の道を選んだのである。それは、倒幕という壮大な目標を達成するために、既存の秩序に囚われない、自由な発想と行動が必要だと悟っていたからに他ならない。\n\n亀山社中の設立は、単なる利潤追求を目的としたものではなかった。龍馬の構想は、遥かに壮大であった。彼は、亀山社中を、倒幕のための武器調達の拠点とし、また、志士たちの活動資金を調達するための機関として位置づけた。薩摩藩や長州藩といった、倒幕を目指す諸藩との間で、武器や物資の仲介を行い、その手数料を活動資金に充てたのである。\n\nこれは、当時としては画期的な発想であった。武力による倒幕を目指す一方で、経済的な基盤を確立し、自立した組織として活動すること。龍馬は、武士の矜持と商人の才覚を併せ持ち、未来を見据える先見性を持っていた。彼の頭の中には、すでに新しい日本国の設計図が描かれていたのかもしれない。\n\n亀山社中の活動は、多岐にわたった。武器弾薬の調達、船舶の購入、さらには外国商社との交渉まで、その業務は、当時の日本の常識を遥かに凌駕するものであった。龍馬は、自ら外国語を学び、異国の文化や技術にも積極的に触れた。彼は、日本を鎖国という殻から解き放ち、世界に伍する国にするためには、何が必要かを知っていたのである。\n\n長崎の亀山社中の拠点は、倒幕を目指す志士たちの梁山泊ともなった。土佐、薩摩、長州、そして幕府側からも、様々な立場の人間が集い、夜な夜な日本の未来について熱く語り合った。龍馬は、その中心にあって、彼らの思想をまとめ上げ、具体的な行動へと導いた。彼の周りには、いつしか、身分や藩の垣根を越え、日本の未来を憂う若者たちが集まっていたのである。\n\nしかし、亀山社中の活動は、常に危険と隣り合わせであった。幕府からの監視、他藩からの妨害、そして内部の不和。龍馬は、これらの困難に真正面から立ち向かった。彼の信念は揺るがず、その行動力は、周囲の人間を巻き込み、不可能を可能にする力を持っていた。\n\n龍馬は、亀山社中を通じて、単に倒幕のための物資を調達するだけでなく、新しい日本のあり方を模索していた。彼は、武力による解決だけでなく、経済的な自立と、国際社会との共存が、これからの日本には不可欠だと考えていたのである。彼の構想は、当時の日本人の常識を遥かに超えた、壮大なものであった。\n\n亀山社中という組織は、龍馬の独創的な発想と、類まれなる行動力によって生まれた、まさに夜明けの夢であった。それは、閉塞した時代を打ち破り、新しい日本を切り開くための、希望の光であった。利潤追求ではなく、倒幕という大義のために、武士の身分を捨て、商人の道を選んだ龍馬の選択は、彼の生涯において、そして日本の歴史において、極めて重要な転換点となったのである。\n\n龍馬は、亀山社中の活動を通じて、多くのことを学んだ。国際情勢、経済の仕組み、そして人との繋がり。彼は、これらの経験を糧に、さらに大きな理想へと向かっていく。亀山社中は、彼の目指す「日本国」の、最初の青写真であったと言えるだろう。\n\nそして、この亀山社中の精神は、やがて、さらに公的な性格を帯びた組織へと発展していく。それが、龍馬が人生の全てを賭けた、もう一つの理想の結晶、「海援隊」である。亀山社中という夜明けの夢は、やがて、日本という国の未来を背負う、壮大な船出へと繋がっていくのである。彼の描いた理想は、まだ道半ばであったが、その萌芽は、この長崎の地で、確かに芽吹き始めていた。",
      "image_prompts": [
        "historic Japanese samurai dojo, Chiba dojo, Edo period, wooden swords, intense training",
        "historic Japanese samurai concentration, blurred background, close up of eyes",
        "historic Japanese martial arts practice, ink wash painting style, traditional atmosphere"
      ]
    },
    {
      "index": 3,
      "title": "海援隊に託した日本国の設計図",
      "narration": "土佐の鏡川は、今も変わらぬ静けさで流れている。\nあの頃、この川のほとりで、坂本龍馬という男は、己の進むべき道を模索していた。\n脱藩という、己の全てを捨て去る覚悟。それは、単なる反逆ではなかった。\n新たな日本の夜明けを、その両の腕で掴み取ろうとする、烈火のごとき決意の表明であった。\n\n長崎の港に、龍馬はいた。\n異国の船がひしめき合い、異国の言葉が飛び交う、活気と混沌の坩堝。\nここで、彼は「亀山社中」を立ち上げた。\nそれは、単なる商社ではない。\n倒幕という、巨大な目的を達成するための、龍馬ならではの仕掛けであった。\n武器を調達し、同志を集め、情報網を築く。\n利潤を追求するのではなく、革命という大義のための、実働部隊。\nその構想こそが、亀山社中を、時代を映す鏡たらしめていた。\n\nしかし、龍馬の目は、すでにその先を見ていた。\n武力だけでは、この国は救えない。\n長崎の異国情緒に触れるうち、龍馬の胸に、新たな灯火が灯り始めた。\nそれは、世界という広大な視野であった。\n国際社会のルール、万国公法。\nそれを学び、理解することこそが、未来の日本が歩むべき道であると。\n\n亀山社中を、さらに発展させる形で、龍馬は「海援隊」を設立する。\nその名は、海を渡る船団の如く、日本を世界へと導く意思を宿していた。\n海援隊は、より公的な性格を帯び、その活動範囲は広がりを見せる。\n単なる武器調達に留まらず、貿易、外交。\nそこには、龍馬の、日本という国家の在り方そのものへの、深い洞察があった。\n\n彼は、旧来の身分制度や、鎖国という閉鎖的な考え方を、鋭く見抜いていた。\n世界は、すでに大きく動いている。\nその波に乗り遅れることなく、むしろ、その波を自らの力に変えていく。\nそのためには、国際社会の一員として、正当な権利と義務を果たす必要がある。\n万国公法は、そのための羅針盤であった。\n\n龍馬は、剣の腕だけでなく、その頭脳をも駆使した。\n商才、交渉術、そして何よりも、人を惹きつける魅力。\nそれら全てを、海援隊という器に注ぎ込んだ。\nそれは、彼が夢見た、新しい日本の設計図であった。\n外国との対等な関係を築き、自らの力で富を築き、そして、自由な精神が息づく国。\n\n海援隊の船は、長崎の港から、ゆっくりと進み始める。\nその帆には、坂本龍馬の、熱き魂が宿っていた。\n彼は、己の命を賭して、この国の未来を、照らし出そうとしていたのだ。\n武力だけでは成し遂げられない、理想の国家。\nその実現のために、龍馬は、海援隊に、全てを託した。\n\n旧態依然とした幕府の権力。\nそれを、力でねじ伏せるだけでは、本当の解決にはならない。\n龍馬の思想は、その先を見据えていた。\n万国公法を学ぶことは、単なる知識の習得ではない。\nそれは、人間としての理性、そして、国家としての尊厳を、再定義する行為であった。\n\n海援隊の船影は、長崎の水平線に、悠然と消えていく。\nその背中には、日本の夜明けを信じる、一人の男の、壮大なロマンが、確かに刻まれていた。\n彼は、武士の魂を守りながらも、その枠を超えようとした。\n侍の美学とは、単なる古き良き伝統ではない。\nそれは、変化を恐れず、常に高みを目指す、不屈の精神の現れである。\n\n坂本龍馬。\n亀山社中、そして海援隊。\nその理想は、単なる過去の遺物ではない。\n現代を生きる我々にも、なお、問いかけ続けている。\n国家とは何か。\n自由とは何か。\nそして、侍の魂とは、この時代に、いかなる意味を持つのか。\n\n海援隊は、その名を轟かせた。\nしかし、龍馬の真の功績は、その名声だけではない。\nそれは、彼が残した、未来への確かな設計図。\n万国公法を学び、世界と渡り合うための、開かれた精神。\nその思想こそが、海援隊という船に、永遠の価値を与えているのだ。\n\n龍馬の瞳には、常に、広大な海が映っていた。\nその海は、彼に、自由と可能性を示唆していた。\nそして、その海を渡るための、強靭な意思を、龍馬に与えていた。\n海援隊は、その意思の、具体的な形であった。\n日本という国を、世界に恥じぬ国にするための、龍馬の、情熱的な挑戦であった。\n\n彼は、誰よりも早く、時代の変化を察知した。\nそして、その変化に対応するため、自らを、そして己の組織を、変革させた。\n武力による革命ではなく、対話と共存による、新たな秩序の創造。\nその視点こそが、坂本龍馬を、類稀なる偉人たらしめている所以である。\n海援隊は、その壮大なビジョンを、現実のものとするための、龍馬の、渾身の試みであった。",
      "image_prompts": [
        "historic Japanese Kurofune, black ship arrival, Uraga port, massive steamship in 19th century",
        "historic Japanese young Ryoma looking at the sea, silhouette against the horizon",
        "historic Japanese ocean view, traditional woodblock print style, dramatic waves"
      ]
    },
    {
      "index": 4,
      "title": "船上の夢、消えぬ志",
      "narration": "薩長同盟。その名が歴史の表舞台に刻まれる時、人は龍馬の知略を称え、その手腕を英雄のそれとして賛美する。しかし、その偉業の裏側で、龍馬の心がいかに削られ、いかなる孤独を噛み締めていたかを知る者は少ない。京の宿で、龍馬が吐き出した溜息の重さを、誰が計り得たであろうか。彼は知っていたのだ。この同盟が、血を流し合う同胞同士を繋ぎ止めるための、あまりにも危うい架け橋であることを。\n\n長年、反目し合ってきた薩摩と長州。その両者の手を取り合わせることは、単なる政治の駆け引きではない。それは、日本という国を解体し、再構築するという、神の領域にも等しい荒技であった。亀山社中という夜明けの夢を抱き、長崎の海風を肌で感じていた龍馬にとって、大陸から押し寄せる列強の影は、いつ壊れてもおかしくない日本の姿そのものであった。だからこそ、彼は自らの立場を捨て、個の利益を超越し、ただ未来という一点のみを見据えたのである。\n\n龍馬が抱えていたのは、勝つための戦略ではない。負けないための設計図であった。武力による対立の先に、どれほどの希望があるというのか。彼は海援隊に託した日本国の設計図を心に描きながら、自らの命が消耗品であることを悟っていたはずだ。海援隊とは、単なる武装集団でもなければ、利潤を追う商社でもない。それは、日本という国が初めて手にする、世界へ向けての開かれた窓であった。\n\n海援隊という名には、海を越えて世界と対峙する、新しい日本人の誇りが込められている。龍馬は船上で、ただ波の音を聞き、星の瞬きを眺めていた。その時、彼の脳裏をよぎったのは、斬り合いの血の匂いではなく、遥か遠い異国の港の風景であったのかもしれない。彼が夢見た未来は、誰の支配も受けず、誰の首も取ることのない、自由な通商の海である。武士という身分を解体し、誰もが志を立てて生きられる世の中。それが、龍馬の追い求めた究極の平和であった。\n\nしかし、現実はあまりに冷徹であった。薩長同盟を成し遂げたとしても、そこから続く道は、暗い霧に包まれていた。龍馬の足跡を追う者は増え、彼の首を狙う者の刃もまた、すぐそこまで迫っていた。亀山社中での苦難、海援隊での理想追求。そのすべてが、歴史の奔流の中に飲み込まれようとしていた。彼は、自分の死を予感していたのだろうか。手紙に書き綴られた言葉の端々に、漂う哀愁。それは、自らの最期を見極めた者だけが持つ、静かな達観の表れであった。\n\n京都、近江屋の冷たい畳の上で、龍馬は何を思ったか。暗殺という悲劇的な結末は、彼にとっては唐突な終わりではなく、ある種の必然であったのかもしれない。志のために己の身を捧げ、日本という国家の礎石となる。それは、侍という存在が到達し得る、最も過酷で、最も美しい美学の極致である。彼が夢見た船上の旅は、ここで終わりを迎える。だが、その夢の続きを、私たちは今も追い続けているのではないか。\n\n龍馬の生き様は、現代を生きる我々に、一つの問いを突きつける。私たちは、自分のためではなく、未来のために、どれだけの情熱を燃やせているのかと。暗闇の中で、龍馬は笑っていたはずだ。最期の瞬間まで、彼は日本という国を信じていた。海援隊の同志たちに託した言葉は、今も風に乗って、日本の海を渡り続けている。自由とは何か、平和とは何かという、答えのない問いに対する、龍馬なりの解答。\n\n暗殺の夜、京の空に浮かんだ月は、彼が生まれ育った土佐の鏡川の月と、同じ色をしていたに違いない。血を流し、夢を語り、時代を駆け抜けた男。坂本龍馬という存在は、特定の思想や組織に縛られることを拒んだ。彼は、ただ日本という国そのものに恋をした、一人の若者であったのだ。海援隊の理想も、亀山社中の夢も、すべては彼が心から愛したこの国の未来へと繋がっている。\n\n彼は、己の命と引き換えに、何を遺したのか。それは、権力への執着ではない。名誉への渇望でもない。ただ、自由に生き、自由に死ぬという、人間として最も尊い誇りである。龍馬という男がいたからこそ、日本は新しい時代へと舵を切ることができた。その舵を握っていたのは、たった一人の志士の、震えるような情熱であった。船上の夢は消えてしまったのではない。それは、この国の未来という海の中に、永遠に溶け込んでいるのだ。\n\n歴史の波に揉まれながら、それでも彼は笑い続けた。その笑顔の裏にあったのは、計り知れない葛藤と、それを飲み込むほどの深い愛であった。侍とは、死ぬために生きるのではない。生きた証を、未来という名の帆に書き記すために、命の火を燃やす者のことである。龍馬の生涯は、まさにその体現であった。彼は、己の身を切り売りしながら、この国の夜明けを、その両手で手繰り寄せたのである。\n\n今、私たちが享受しているこの平和な空の下で、龍馬は何を語るだろうか。おそらく彼は、肩をすくめてこう言うはずだ。まだ終わっていない、と。船はまだ、荒波の真っ只中にいる。その先にあるのは、誰かのための未来ではなく、あなた自身の志によって開かれる、新しい海である、と。龍馬の夢は、決して過去の記録の中に閉じ込められてはいない。それは、今を生きる我々の心の中に、今も静かに波打っている。\n\n坂本龍馬。その名は、歴史という名の広大な海を航海し続ける、一隻の魂の船である。彼は、己の命が尽きるその瞬間まで、帆を降ろすことはなかった。どんなに激しい嵐が吹き荒れようとも、彼が目指した地平は、常に自由と平和に満ちていた。その執念は、暗殺という悲劇を乗り越え、時代を超えて、我々の魂を揺さぶり続ける。彼の美学は、決して消えることのない、一閃の光となって、今も日本の夜空を照らし出している。\n\n亀山社中、そして海援隊。その二つの旗印の下に集った男たちの熱い想いは、龍馬という磁石に引き寄せられた、魂の巡礼であった。彼は、誰も見たことのない未来を夢見た。そして、その夢を現実のものとするために、すべてを賭けた。失敗を恐れず、裏切りを許し、ただ志のみを道標として歩んだ男。その生涯に一点の曇りなし。彼は、侍としての誇りを、その背中で語り続けたのである。\n\n龍馬が遺したものは、言葉ではない。彼が示したのは、生き方そのものである。どう生きるか、何のために死ぬか。その問いに対して、彼は沈黙のうちに、しかし強烈に答えを残した。海援隊という組織が、日本の夜明けを告げる鐘となったように、龍馬という一人の男の生き様は、今も我々の心の中で、高らかに鳴り響いている。船上の夢、消えぬ志。それは、この国が続く限り、決して色あせることのない、永遠の航海図である。\n\n最後に、龍馬の瞳を思い出してほしい。そこには、絶望の影はなく、ただ未来への渇望だけが宿っていた。彼は、自分の命を、国という大きな器の中に投げ入れた。その器から溢れ出した希望の雫が、今の日本を形作っている。坂本龍馬という男の、海よりも深く、空よりも広いその魂に、今こそ、静かに想いを馳せたい。彼が夢見た日本の、その続きを生きる我々にできることは、彼が愛したこの国を、より美しく、より誇り高い場所へと導くことだけなのだから。\n\n波は繰り返す。しかし、同じ波は二度と訪れない。だからこそ、今というこの瞬間を、龍馬のように真っ直ぐに生きること。それこそが、彼が遺した侍の美学への、最も誠実な答えである。彼の夢は、海から空へ、空から人の心へと、形を変えて受け継がれていく。坂本龍馬、その名は永遠の航海者として、我々が迷い込んだ霧の中を、静かに、そして確実に、光の射す方向へと導いてくれるだろう。",
      "image_prompts": [
        "historic Japanese Nagasaki port, merchant ships, early Meiji era aesthetics",
        "historic Japanese Kameyama Shachu office, group of samurais planning, dim lighting",
        "historic Japanese trading company, merchant ships, maritime history scene"
      ]
    },
    {
      "index": 5,
      "title": "龍馬が遺した侍の魂の在り処",
      "narration": "土佐の風に吹かれ、海を見つめ、ただひたすらに日本の明日を案じた男。坂本龍馬という一人の志士が、その短い生涯を駆け抜けた果てに、我々は何を見出すべきか。それは単なる歴史の一頁に記された英雄伝ではない。己の魂を、国家という名の巨大な器に捧げた、一人の侍の生き様そのものである。\n\n龍馬が遺したものは、何一つ形ある資産ではない。それは、亀山社中の結成から始まった、組織の枠を超えて思考する力である。当時の日本において、藩という組織は絶対の境界線であった。主君に仕え、藩の利益を守ることが武士の美学のすべてと信じられていた時代。しかし龍馬は、その境界を軽々と踏み越えた。\n\n脱藩という名の叛逆。それは、個人の身勝手な振る舞いではなく、藩という閉ざされた世界を飛び出し、日本という一つの国を鳥の目で見つめるための決断であった。彼が求めたのは、個人の名誉でも、特定の勢力の勝利でもなかった。ただ、この国が列強の波に飲み込まれず、対等に渡り合えるだけの強さと誇りを持つこと。それこそが、彼の掲げた究極の理想であった。\n\n亀山社中、そして海援隊。これらの組織が彼にとって何を意味していたのか。それは単なる海運や貿易の拠点ではない。龍馬が夢見たのは、万国公法に裏打ちされた文明国家の雛形であり、志を同じくする者が身分や派閥を捨てて集う、真の同志の結社であった。組織とは、人が志を実現するための器に過ぎない。龍馬は、その器をいかにしなやかに操り、目的のために変幻自在に形を変えるかを、誰よりも深く理解していた。\n\n現代を生きる我々は、組織の論理に縛られ、しばしば木を見て森を見失う。所属する会社、属する集団、日々の細かな利害関係。それらに埋没し、本来自分たちが成し遂げたかったはずの大きな目的を忘れてはいないか。龍馬の生涯は、我々に問いかける。お前は、何のために生き、何を成し遂げようとしているのか、と。\n\n坂本龍馬という男の凄みは、その先見性にあった。彼は、来るべき時代が、力による支配の時代ではなく、知恵と外交、そして広範なネットワークが国を動かす時代であることを予見していた。海援隊の精神には、単なる倒幕という短期的な目標を超えた、新しい日本を設計しようとする深い思索が流れている。彼は、刀を抜くことよりも、対話によって局面を打開することの困難さと、その尊さを誰よりも知っていた。\n\n薩長同盟という偉業も、彼が目指した全体最適の視点から見れば、必然の帰結であった。憎しみ合う者同士を繋ぎ、共通の未来を語らせる。そのためには、己の命がいくつあっても足りないという覚悟が必要であった。龍馬の美学とは、己の小さなプライドや個人的な恨みを、国家の進むべき道のために潔く捨て去る、その究極の無私にあったと言える。\n\n暗殺という結末は、あまりにも残酷で、あまりにも早すぎる幕切れであった。しかし、その死すらも、彼が全身全霊で駆け抜けた人生の彩りであったかのように見える。命を奪われるその瞬間まで、龍馬は夢を見ていた。日本の夜明けを、誰もが誇りを持って生きられる国の姿を。その志は、彼が遺した言葉や行動を通じて、今もなお我々の胸に熱い灯火を投げかけている。\n\n先見性とは、単なる予測ではない。それは、未来を自らの手で切り拓こうとする意志の強さである。龍馬は、誰かが変えてくれるのを待つのではなく、自らが先頭に立ち、荒波を漕ぎ出す先駆者であった。たとえ無数の批判を浴びようとも、己の信じる道を進み続けること。それが、龍馬が身をもって体現した、侍の美学の神髄である。\n\n我々が今日、平和な社会を享受しているのは、先人たちが流した血と汗、そして龍馬のように、国家の未来を憂い、己の全てを賭して戦った者たちがいたからに他ならない。しかし、彼らが夢見た日本は、完成されたものではない。常に時代とともに変化し、問い直し、作り上げていくものだ。その責任は、今を生きる我々の双肩にかかっている。\n\n坂本龍馬という男の生涯を通じ、我々は改めて学ぶべきだ。組織の枠組みや、世間の常識に囚われてはならない。真に大切なのは、己の中に流れる志であり、他者と共に夢を語り合い、未来を創造しようとする情熱である。彼が亀山社中で見つめていた海は、今も変わらず世界へと続いている。海援隊が理想とした自由と対話の精神は、今こそ我々に必要とされている。\n\n龍馬は、時代の寵児として祭り上げられることを望まなかっただろう。彼はただ、一人の侍として、誠実に、そして熱く、日本という国の可能性を信じ抜いた。その誠実さこそが、彼の最大の武器であり、現代を生きる我々にとっても、最も欠けている羅針盤なのかもしれない。己の心に嘘をつかず、誰に対しても開かれた魂を持つこと。それこそが、侍の魂の在り処である。\n\n時は流れ、時代は変わった。しかし、人間が成し遂げるべき大きな目的というものは、いつの時代も変わらない。困難に直面したとき、迷いが生じたとき、我々はいつでも龍馬の姿を思い浮かべればよい。あの男なら、この局面で何を考え、どう動くのか。そう自問自答した瞬間、目の前の霧は晴れ、進むべき道が照らし出されるはずだ。\n\n坂本龍馬。その名を聞くたびに、我々の心には一筋の風が吹く。それは、土佐の山々を越え、広大な海を渡り、新しい時代を運んできた、未来からの風である。彼は死してなお、我々に語りかけている。この国を、もっと誇れる場所にするために、お前は何を成すのかと。\n\n彼の遺した志は、決して色褪せることはない。海援隊の旗印に込められた、自由と平和への願い。それは、今もこの国の空に、海に、そして我々一人ひとりの魂の中に、脈々と受け継がれている。志のために己を捧げた、一人の侍の美学。その高潔な生き様を胸に、我々もまた、それぞれの時代における夜明けを目指して歩み続けなければならない。\n\nさあ、顔を上げよう。龍馬が見つめたその先には、まだ誰も知らない新しい景色が広がっている。過去を振り返る暇などない。彼がそうであったように、我々もまた、今この瞬間から、未来を設計し、歴史を刻む者となるのだ。坂本龍馬という、日本史上最も鮮烈な志士の魂をその身に宿して。\n\n日本という国は、これからも幾多の困難に直面するだろう。しかし、そのたびに我々は思い出すはずだ。亀山社中の狭い部屋で、あるいは海援隊の船上で、夜通し日本の明日を熱く語り合った、あの男の瞳を。彼の魂は、我々が志を失わない限り、永遠に生き続ける。侍の美学とは、絶望の淵にあってもなお、希望の光を灯し続けること。坂本龍馬、その生き様こそが、日本という国の誇りであり、未来への道標である。\n\n我々は歩む。彼が愛したこの国の、さらなる高みを目指して。組織の殻を破り、個人の限界を超え、日本という国そのものを憂い、愛する力を持って。龍馬が夢見た夜明けは、遠い過去の話ではない。それは、我々が志を新たにするたびに、何度でもこの国に訪れる希望の光なのだ。侍の魂は、終わることのない挑戦の中にこそ、永遠に息づいている。",
      "image_prompts": [
        "historic Japanese Kaientai emblem, maritime flag, ocean waves, cinematic lighting",
        "historic Japanese Ryoma Sakamoto looking over the ocean, sunset, iconic pose",
        "historic Japanese futuristic vision, conceptual art, ships sailing into the bright future"
      ]
    }
  ],
  "total_chars": 13023,
  "target_chars_min": 9600,
  "target_chars_max": 12000,
  "generated_at": "2026-05-21T22:50:46.376Z",
  "generator": "bulk_generate_scripts.mjs v1"
}