{
  "archive_CCgFjnDlxvM_peak": {
    "videoId": "DFvfLRpA3CM",
    "videoUrl": "https://youtube.com/shorts/DFvfLRpA3CM",
    "title": "【心理学】言葉にしない愛情表現｜静かな愛が深く届く科学 #Shorts 感動",
    "uploadedAt": "2026-05-30T04:10:03.646Z",
    "source": "upload_shorts"
  },
  "archive_LAVSg_jvnkY_peak": {
    "videoId": "SBPFvMvtemk",
    "videoUrl": "https://youtube.com/shorts/SBPFvMvtemk",
    "title": "【心理学】心理的安全性が高い関係の作り方｜信頼の科学と実践 #Shorts 感動",
    "uploadedAt": "2026-05-30T04:10:36.212Z",
    "source": "upload_shorts"
  },
  "archive_OdK_Z-qOWOY_peak": {
    "videoId": "O4RcWdYImuc",
    "videoUrl": "https://youtube.com/shorts/O4RcWdYImuc",
    "title": "肌が触れた瞬間に脳が記憶する官能の科学 #Shorts 感動",
    "uploadedAt": "2026-05-30T04:11:09.476Z",
    "source": "upload_shorts"
  },
  "archive_-mDkSwQDiMI_intro": {
    "videoId": "UQQC6Pwo26U",
    "videoUrl": "https://youtube.com/shorts/UQQC6Pwo26U",
    "title": "30代女性が知っておきたい大人の恋愛心理学 #Shorts 導入",
    "uploadedAt": "2026-05-30T04:23:15.456Z",
    "source": "upload_shorts"
  },
  "archive_-mDkSwQDiMI_outro": {
    "videoId": "3GmXEJeNL10",
    "videoUrl": "https://youtube.com/shorts/3GmXEJeNL10",
    "title": "30代女性が知っておきたい大人の恋愛心理学 #Shorts 結末",
    "uploadedAt": "2026-05-30T04:23:47.721Z",
    "source": "upload_shorts"
  }
}