{
  "010": {
    "videoId": "RZq9llbHwdg",
    "videoUrl": "https://youtube.com/shorts/RZq9llbHwdg",
    "title": "otona_shorts 010",
    "uploadedAt": "2026-05-29T07:07:44.004Z",
    "source": "upload_quarantine"
  },
  "012": {
    "videoId": "xRwsoaLG9CQ",
    "videoUrl": "https://youtube.com/shorts/xRwsoaLG9CQ",
    "title": "otona_shorts 012",
    "uploadedAt": "2026-05-29T07:08:16.879Z",
    "source": "upload_quarantine"
  },
  "014": {
    "videoId": "sFSwoJXuDWA",
    "videoUrl": "https://youtube.com/shorts/sFSwoJXuDWA",
    "title": "otona_shorts 014",
    "uploadedAt": "2026-05-29T07:08:49.524Z",
    "source": "upload_quarantine"
  },
  "015": {
    "videoId": "Fdura5dH4Qw",
    "videoUrl": "https://youtube.com/shorts/Fdura5dH4Qw",
    "title": "otona_shorts 015",
    "uploadedAt": "2026-05-29T07:09:22.005Z",
    "source": "upload_quarantine"
  },
  "016": {
    "videoId": "xtQde66p21M",
    "videoUrl": "https://youtube.com/shorts/xtQde66p21M",
    "title": "otona_shorts 016",
    "uploadedAt": "2026-05-29T07:09:55.403Z",
    "source": "upload_quarantine"
  },
  "017": {
    "videoId": "uBb3WoHgb0E",
    "videoUrl": "https://youtube.com/shorts/uBb3WoHgb0E",
    "title": "otona_shorts 017",
    "uploadedAt": "2026-05-29T07:10:29.117Z",
    "source": "upload_quarantine"
  }
}